LICENSE
MANIFEST.in
README
chiki_wxpay.py
setup.py
chiki_wxpay.egg-info/PKG-INFO
chiki_wxpay.egg-info/SOURCES.txt
chiki_wxpay.egg-info/dependency_links.txt
chiki_wxpay.egg-info/not-zip-safe
chiki_wxpay.egg-info/requires.txt
chiki_wxpay.egg-info/top_level.txt