Metadata-Version: 1.0
Name: chiki-wxpay
Version: 0.0.1
Summary: chiki wxpay libs.
Home-page: https://github.com/endsh/chiki-wxpay
Author: Linshao
Author-email: 438985635@qq.com
License: UNKNOWN
Platform: any
